odoo8_addon_account_financial_report_webkit-8.0.1.2.1-py2.7-nspkg.pth
odoo8_addon_account_financial_report_webkit-8.0.1.2.1.dist-info/DESCRIPTION.rst
odoo8_addon_account_financial_report_webkit-8.0.1.2.1.dist-info/METADATA
odoo8_addon_account_financial_report_webkit-8.0.1.2.1.dist-info/RECORD
odoo8_addon_account_financial_report_webkit-8.0.1.2.1.dist-info/WHEEL
odoo8_addon_account_financial_report_webkit-8.0.1.2.1.dist-info/metadata.json
odoo8_addon_account_financial_report_webkit-8.0.1.2.1.dist-info/namespace_packages.txt
odoo8_addon_account_financial_report_webkit-8.0.1.2.1.dist-info/top_level.txt
odoo_addons/account_financial_report_webkit/README.rst
odoo_addons/account_financial_report_webkit/__init__.py
odoo_addons/account_financial_report_webkit/__openerp__.py
odoo_addons/account_financial_report_webkit/account_view.xml
odoo_addons/account_financial_report_webkit/report_menus.xml
odoo_addons/account_financial_report_webkit/data/financial_webkit_header.xml
odoo_addons/account_financial_report_webkit/i18n/de.po
odoo_addons/account_financial_report_webkit/i18n/en_US.po
odoo_addons/account_financial_report_webkit/i18n/es.po
odoo_addons/account_financial_report_webkit/i18n/es_ES.po
odoo_addons/account_financial_report_webkit/i18n/fr.po
odoo_addons/account_financial_report_webkit/i18n/it.po
odoo_addons/account_financial_report_webkit/i18n/lt.po
odoo_addons/account_financial_report_webkit/i18n/nl.po
odoo_addons/account_financial_report_webkit/i18n/sl.po
odoo_addons/account_financial_report_webkit/images/ledger.png
odoo_addons/account_financial_report_webkit/migrations/7.0.1.0.2/post-migration.py
odoo_addons/account_financial_report_webkit/migrations/8.0.1.2.0/post-migration.py
odoo_addons/account_financial_report_webkit/models/__init__.py
odoo_addons/account_financial_report_webkit/models/account.py
odoo_addons/account_financial_report_webkit/models/account_move_line.py
odoo_addons/account_financial_report_webkit/report/__init__.py
odoo_addons/account_financial_report_webkit/report/aged_open_invoices.py
odoo_addons/account_financial_report_webkit/report/aged_partner_balance.py
odoo_addons/account_financial_report_webkit/report/common_balance_reports.py
odoo_addons/account_financial_report_webkit/report/common_partner_balance_reports.py
odoo_addons/account_financial_report_webkit/report/common_partner_reports.py
odoo_addons/account_financial_report_webkit/report/common_reports.py
odoo_addons/account_financial_report_webkit/report/general_ledger.py
